<?xml version="1.0" encoding="UTF-8"?>
<nifty xmlns="http://nifty-gui.lessvoid.com/nifty-gui">
  <useStyles filename="nifty-default-styles.xml" />
  <useControls filename="nifty-default-controls.xml" />
  <screen id="start" controller="de.lessvoid.nifty.examples.reload.ReloadScreen">
    <layer id="layer" backgroundColor="#003f" childLayout="center">
      <panel id="panel" height="25%" width="35%" align="center" valign="center" backgroundColor="#f60f" childLayout="center" visibleToMouse="true">
        <interact onClick="loadNext()"/>
        <text id="text" font="aurulent-sans-16.fnt" color="#000f" text="Next!" align="center" valign="center" />
      </panel>
    </layer>
  </screen>
</nifty>